ibarrow-0.1.9.dist-info/METADATA
ibarrow-0.1.9.dist-info/WHEEL
ibarrow-0.1.9.dist-info/licenses/LICENSE
ibarrow.libs/libltdl-f059d7bf.so.7
ibarrow.libs/libodbc-e3053cde.so.2
ibarrow/__init__.py
ibarrow/ibarrow.cpython-312-x86_64-linux-gnu.so
ibarrow-0.1.9.dist-info/RECORD
