Metadata-Version: 2.4
Name: ibarrow
Version: 0.1.9
Classifier: Development Status :: 4 - Beta
Classifier: Intended Audience :: Developers
Classifier: License :: OSI Approved :: MIT License
Classifier: Programming Language :: Python :: 3
Classifier: Programming Language :: Python :: 3.8
Classifier: Programming Language :: Python :: 3.9
Classifier: Programming Language :: Python :: 3.10
Classifier: Programming Language :: Python :: 3.11
Classifier: Programming Language :: Python :: 3.12
Classifier: Programming Language :: Rust
Classifier: Topic :: Database
Classifier: Topic :: Software Development :: Libraries
Requires-Dist: pyarrow>=10.0.0
Requires-Dist: polars>=0.19.0
Requires-Dist: python-dotenv>=0.19.0 ; extra == 'dev'
Requires-Dist: pytest>=7.0.0 ; extra == 'dev'
Requires-Dist: pytest-cov>=4.0.0 ; extra == 'dev'
Requires-Dist: version ; extra == 'dynamic'
Provides-Extra: dev
Provides-Extra: dynamic
License-File: LICENSE
Summary: High-performance ODBC to Arrow data connector for InterBase/Firebird
Keywords: odbc,arrow,database,interbase,firebird,performance
Author-email: Thomaz Yuji Baba <thomaz.yuji@gmail.com>
License: MIT
Requires-Python: >=3.8
Project-URL: Homepage, https://github.com/thomazyujibaba/ibarrow
Project-URL: Repository, https://github.com/thomazyujibaba/ibarrow
Project-URL: Issues, https://github.com/thomazyujibaba/ibarrow/issues
